pysnr/__init__.py
pysnr/sfdr.py
pysnr/sinad.py
pysnr/snr.py
pysnr/thd.py
pysnr/toi.py
pysnr/utils.py
pysnr-0.0.1.dist-info/LICENSE
pysnr-0.0.1.dist-info/METADATA
pysnr-0.0.1.dist-info/WHEEL
pysnr-0.0.1.dist-info/top_level.txt
pysnr-0.0.1.dist-info/RECORD
