Metadata-Version: 2.1
Name: pysnr
Version: 0.0.1
Summary: A suite of tools performing noise analysis
Home-page: https://github.com/psambit9791/pysnr
Author: Sambit Paul
Author-email: sambitpaul1992@gmail.com
Classifier: Programming Language :: Python :: 3
Classifier: License :: OSI Approved :: MIT License
Classifier: Operating System :: OS Independent
Requires-Python: >=3.8
License-File: LICENSE
Requires-Dist: numpy (~=1.22)
Requires-Dist: scipy (~=1.8.1)
